hop3_installer/__init__.py
hop3_installer/bundler.py
hop3_installer/common.py
hop3_installer/main.py
hop3_installer/cli_installer/__init__.py
hop3_installer/cli_installer/checks.py
hop3_installer/cli_installer/cli.py
hop3_installer/cli_installer/config.py
hop3_installer/cli_installer/installer.py
hop3_installer/cli_installer/python.py
hop3_installer/cli_installer/shell.py
hop3_installer/cli_installer/verify.py
hop3_installer/deployer/__init__.py
hop3_installer/deployer/cli.py
hop3_installer/deployer/config.py
hop3_installer/deployer/deploy.py
hop3_installer/deployer/backends/__init__.py
hop3_installer/deployer/backends/base.py
hop3_installer/deployer/backends/docker.py
hop3_installer/deployer/backends/ssh.py
hop3_installer/server_installer/__init__.py
hop3_installer/server_installer/acme.py
hop3_installer/server_installer/cli.py
hop3_installer/server_installer/config.py
hop3_installer/server_installer/deps.py
hop3_installer/server_installer/deps_common.py
hop3_installer/server_installer/deps_debian.py
hop3_installer/server_installer/deps_fedora.py
hop3_installer/server_installer/installer.py
hop3_installer/server_installer/mysql.py
hop3_installer/server_installer/nginx.py
hop3_installer/server_installer/postgres.py
hop3_installer/server_installer/python.py
hop3_installer/server_installer/redis.py
hop3_installer/server_installer/services.py
hop3_installer/server_installer/ssl.py
hop3_installer/server_installer/user.py
hop3_installer/server_installer/verify.py
hop3_installer/testing/__init__.py
hop3_installer/testing/cli.py
hop3_installer/testing/common.py
hop3_installer/testing/runner.py
hop3_installer/testing/validators.py
hop3_installer/testing/backends/__init__.py
hop3_installer/testing/backends/base.py
hop3_installer/testing/backends/docker.py
hop3_installer/testing/backends/ssh.py
hop3_installer/testing/backends/vagrant.py
hop3_installer/testing/vagrant/Vagrantfile
hop3_installer/testing/vagrant/Vagrantfile-9p
hop3_installer-0.4.0b1.dist-info/METADATA
hop3_installer-0.4.0b1.dist-info/WHEEL
hop3_installer-0.4.0b1.dist-info/entry_points.txt
hop3_installer-0.4.0b1.dist-info/RECORD
